django_lifecycle/__init__.py
django_lifecycle/abstract.py
django_lifecycle/constants.py
django_lifecycle/dataclass_validation.py
django_lifecycle/decorators.py
django_lifecycle/hooks.py
django_lifecycle/mixins.py
django_lifecycle/model_state.py
django_lifecycle/models.py
django_lifecycle/priority.py
django_lifecycle/py.typed
django_lifecycle/types.py
django_lifecycle/utils.py
django_lifecycle/conditions/__init__.py
django_lifecycle/conditions/base.py
django_lifecycle/conditions/legacy.py
django_lifecycle-1.2.6.dist-info/licenses/LICENSE.md
django_lifecycle_checks/__init__.py
django_lifecycle_checks/apps.py
django_lifecycle_checks/py.typed
django_lifecycle-1.2.6.dist-info/METADATA
django_lifecycle-1.2.6.dist-info/WHEEL
django_lifecycle-1.2.6.dist-info/top_level.txt
django_lifecycle-1.2.6.dist-info/RECORD
