Metadata-Version: 2.4
Name: django-lifecycle
Version: 1.2.6
Summary: Declarative model lifecycle hooks.
Home-page: https://github.com/rsinger86/django-lifecycle
Author: Robert Singer
Author-email: robertgsinger@gmail.com
License: MIT
Project-URL: Documentation, https://rsinger86.github.io/django-lifecycle/
Project-URL: Source, https://github.com/rsinger86/django-lifecycle
Keywords: django model lifecycle hooks callbacks
Classifier: Development Status :: 4 - Beta
Classifier: License :: OSI Approved :: MIT License
Classifier: Programming Language :: Python
Classifier: Programming Language :: Python :: 3.8
Classifier: Programming Language :: Python :: 3.9
Classifier: Programming Language :: Python :: 3.10
Classifier: Programming Language :: Python :: 3.11
Classifier: Programming Language :: Python :: 3.12
Classifier: Framework :: Django
Classifier: Framework :: Django :: 4.2
Classifier: Framework :: Django :: 5.0
Classifier: Framework :: Django :: 5.2
License-File: LICENSE.md
Requires-Dist: Django>=3.2
Dynamic: author
Dynamic: author-email
Dynamic: classifier
Dynamic: description
Dynamic: description-content-type
Dynamic: home-page
Dynamic: keywords
Dynamic: license
Dynamic: license-file
Dynamic: project-url
Dynamic: requires-dist
Dynamic: summary
